Metadata-Version: 2.1
Name: yamale-aac
Version: 3.0.4
Summary: A schema and validator for YAML.
Home-page: https://github.com/danischm/Yamale
Author: Bo Lopker
Author-email: blopker@23andme.com
License: MIT
Platform: UNKNOWN
Classifier: Development Status :: 5 - Production/Stable
Classifier: Intended Audience :: Developers
Classifier: Operating System :: OS Independent
Classifier: License :: OSI Approved :: MIT License
Classifier: Programming Language :: Python
Classifier: Programming Language :: Python :: 3
Classifier: Programming Language :: Python :: 3.4
Requires-Python: >=3.6
Requires-Dist: pyyaml
